hatch_mkdocs/__init__.py
hatch_mkdocs/hatch_hooks.py
hatch_mkdocs/plugin.py
hatch_mkdocs/py.typed
hatch_mkdocs-0.1.0.dist-info/METADATA
hatch_mkdocs-0.1.0.dist-info/WHEEL
hatch_mkdocs-0.1.0.dist-info/entry_points.txt
hatch_mkdocs-0.1.0.dist-info/licenses/LICENSE.md
hatch_mkdocs-0.1.0.dist-info/RECORD
