Metadata-Version: 2.1
Name: hatch-mkdocs
Version: 0.1.0
Summary: Plugin for Hatch to infer env dependencies from mkdocs.yml
Project-URL: Source, https://github.com/mkdocs/hatch-mkdocs
Project-URL: Issues, https://github.com/mkdocs/hatch-mkdocs/issues
Project-URL: History, https://github.com/mkdocs/hatch-mkdocs/releases
Author-email: Oleh Prypin <oleh@pryp.in>
License-Expression: MIT
License-File: LICENSE.md
Keywords: mkdocs
Classifier: Development Status :: 3 - Alpha
Classifier: Environment :: Console
Classifier: Environment :: Web Environment
Classifier: Framework :: Hatch
Classifier: Intended Audience :: Information Technology
Classifier: License :: OSI Approved :: MIT License
Classifier: Operating System :: OS Independent
Classifier: Programming Language :: Python
Classifier: Programming Language :: Python :: 3.8
Classifier: Programming Language :: Python :: 3.9
Classifier: Programming Language :: Python :: 3.10
Classifier: Programming Language :: Python :: 3.11
Classifier: Programming Language :: Python :: 3.12
Classifier: Topic :: Documentation
Classifier: Topic :: Software Development :: Documentation
Classifier: Typing :: Typed
Requires-Python: >=3.8
Requires-Dist: hatch>=1.6.0
Requires-Dist: mkdocs-get-deps>=0.2.0
